README.md
setup.cfg
setup.py
xSL19.py
xinabox_SL19.egg-info/PKG-INFO
xinabox_SL19.egg-info/SOURCES.txt
xinabox_SL19.egg-info/dependency_links.txt
xinabox_SL19.egg-info/requires.txt
xinabox_SL19.egg-info/top_level.txt