Metadata-Version: 2.1
Name: xinabox-SL19
Version: 0.0.7
Summary: Infrared object temperature sensor
Home-page: https://github.com/xinabox/Python-SL19
Author: Luqmaan Baboo
Author-email: luqmaanbaboo@gmail.com
License: UNKNOWN
Platform: UNKNOWN
Classifier: Programming Language :: Python :: 3
Classifier: License :: OSI Approved :: MIT License
Classifier: Operating System :: OS Independent
Requires-Python: >=3.6
